flaskstarter/__init__.py
flaskstarter/flaskstart_cli.py
flaskstarter/templates/.secrets.settings.tomlt
flaskstarter/templates/app.pyt
flaskstarter/templates/blueprint.pyt
flaskstarter/templates/configuration.pyt
flaskstarter/templates/database.pyt
flaskstarter/templates/ext.pyt
flaskstarter/templates/index.htmlt
flaskstarter/templates/manage.pyt
flaskstarter/templates/models.pyt
flaskstarter/templates/settings.tomlt
flaskstarter/templates/views.pyt
flaskstarter/tools/__init__.py
flaskstarter/tools/commands.py
flaskstarter/tools/requirements.py
flaskstarter/tools/templating.py
flaskstarter-0.8.dist-info/LICENSE
flaskstarter-0.8.dist-info/METADATA
flaskstarter-0.8.dist-info/WHEEL
flaskstarter-0.8.dist-info/entry_points.txt
flaskstarter-0.8.dist-info/RECORD
