Metadata-Version: 2.3
Name: flaskstarter
Version: 0.8
Summary: A Flask project start-up CLI to create Flask modular ready projects.
License: Apache-2.0
Keywords: flask,cli,project
Author: Felipe Bastos Nunes
Author-email: felipe.bastosn@gmail.com
Requires-Python: >=3.10,<4.0
Classifier: Development Status :: 3 - Alpha
Classifier: Intended Audience :: Developers
Classifier: Topic :: Software Development :: Build Tools
Requires-Dist: Jinja2 (>=3.1.6,<4.0)
Requires-Dist: MarkupSafe (>=3.0.2,<4.0)
Requires-Dist: click (>=8.2.1,<9.0)
Project-URL: Homepage, https://github.com/felipebastos/flaskstart
Project-URL: Repository, https://github.com/felipebastos/flaskstart
